[
    {
        "name": "onFocus",
        "desc": "Fires when an input component receives focus",
        "exampleDesc": "",
        "usage": {
            "event": "onFocus",
            "source": "inputUsername"
        },
        "propSpec": [
            {
                "key": "source",
                "dataType": "string",
                "mandatory": "no",
                "dft": "script owner id",
                "desc": "The id of the input component we want to listen for focus events on"
            }
        ]
    }
]